kara/__init__.py
kara/_version.py
kara/core.py
kara/splitters.py
kara/integrations/__init__.py
kara/integrations/langchain.py
kara_toolkit-0.2.1.dist-info/licenses/LICENSE
kara_toolkit-0.2.1.dist-info/METADATA
kara_toolkit-0.2.1.dist-info/WHEEL
kara_toolkit-0.2.1.dist-info/top_level.txt
kara_toolkit-0.2.1.dist-info/RECORD
