Metadata-Version: 2.4
Name: kara-toolkit
Version: 0.2.1
Summary: Knowledge-Aware Re-embedding Algorithm - Efficient RAG knowledge base updates
Author-email: Mahdi Zakizadeh <mzakizadeh.me@gmail.com>
License: CC-BY License
Project-URL: Homepage, https://github.com/mzakizadeh/kara
Project-URL: Repository, https://github.com/mzakizadeh/kara
Project-URL: Documentation, https://kara-toolkit.readthedocs.io
Project-URL: Bug Tracker, https://github.com/mzakizadeh/kara-toolkit/issues
Keywords: rag,embeddings,knowledge-base,nlp,langchain,llamaindex
Classifier: Development Status :: 3 - Alpha
Classifier: Intended Audience :: Developers
Classifier: Intended Audience :: Science/Research
Classifier: License :: Other/Proprietary License
Classifier: Programming Language :: Python :: 3
Classifier: Programming Language :: Python :: 3.9
Classifier: Programming Language :: Python :: 3.10
Classifier: Programming Language :: Python :: 3.11
Classifier: Programming Language :: Python :: 3.12
Classifier: Programming Language :: Python :: 3.13
Classifier: Topic :: Scientific/Engineering :: Artificial Intelligence
Classifier: Topic :: Software Development :: Libraries :: Python Modules
Requires-Python: >=3.9
License-File: LICENSE
Requires-Dist: numpy>=1.21.0
Requires-Dist: typing-extensions>=4.0.0
Provides-Extra: langchain
Requires-Dist: langchain>=0.1.0; extra == "langchain"
Requires-Dist: langchain_community>=0.0.1; extra == "langchain"
Requires-Dist: langchain_core>=0.0.1; extra == "langchain"
Requires-Dist: langchain_text_splitters>=0.0.1; extra == "langchain"
Provides-Extra: dev
Requires-Dist: pytest>=7.0.0; extra == "dev"
Requires-Dist: pytest-cov>=4.0.0; extra == "dev"
Requires-Dist: ruff>=0.1.0; extra == "dev"
Requires-Dist: mypy>=1.0.0; extra == "dev"
Requires-Dist: pre-commit>=3.0.0; extra == "dev"
Provides-Extra: all
Requires-Dist: kara-toolkit[dev,langchain]; extra == "all"
Dynamic: license-file
